{
  "comments": {
    "lineComment": "//",
    "blockComment": ["/*", "*/"]
  },
  "brackets": [
    ["{{{", "}}}"],
    ["[[", "]]"],
    ["[", "]"],
    ["(", ")"]
  ],
  "autoClosingPairs": [
    { "open": "{{{", "close": "}}}" },
    { "open": "[[", "close": "]]" },
    { "open": "[", "close": "]" },
    { "open": "(", "close": ")" },
    { "open": "\"", "close": "\"" },
    { "open": "/*", "close": "*/" },
    { "open": "**", "close": "**" },
    { "open": "~~", "close": "~~" },
    { "open": "__", "close": "__" }
  ],
  "surroundingPairs": [
    { "open": "**", "close": "**" },
    { "open": "~~", "close": "~~" },
    { "open": "__", "close": "__" },
    { "open": "[", "close": "]" },
    { "open": "(", "close": ")" },
    { "open": "\"", "close": "\"" }
  ],
  "folding": {
    "markers": {
      "start": "\\{\\{\\{",
      "end": "\\}\\}\\}"
    }
  }
}
