[
  {
    "IfElement": {
      "condition": {
        "Comparison": {
          "left": {
            "NumberLiteral": 5
          },
          "operator": "GreaterThan",
          "right": {
            "NumberLiteral": 3
          }
        }
      },
      "content": [
        {
          "Text": {
            "content": "with delimiter\r"
          }
        },
        {
          "Text": {
            "content": "\n"
          }
        }
      ]
    }
  },
  {
    "Text": {
      "content": "\r"
    }
  },
  {
    "Text": {
      "content": "\n"
    }
  },
  {
    "Text": {
      "content": "\r"
    }
  },
  {
    "Text": {
      "content": "\n"
    }
  },
  {
    "IfElement": {
      "condition": {
        "And": [
          {
            "Group": {
              "Or": [
                {
                  "BoolLiteral": true
                },
                {
                  "BoolLiteral": false
                }
              ]
            }
          },
          {
            "BoolLiteral": true
          }
        ]
      },
      "content": [
        {
          "Text": {
            "content": "grouped condition\r"
          }
        },
        {
          "Text": {
            "content": "\n"
          }
        }
      ]
    }
  },
  {
    "Text": {
      "content": "\r"
    }
  },
  {
    "Text": {
      "content": "\n"
    }
  },
  {
    "Text": {
      "content": "\r"
    }
  },
  {
    "Text": {
      "content": "\n"
    }
  },
  {
    "IfElement": {
      "condition": {
        "Comparison": {
          "left": {
            "Group": {
              "Comparison": {
                "left": {
                  "NumberLiteral": 5
                },
                "operator": "GreaterThan",
                "right": {
                  "NumberLiteral": 3
                }
              }
            }
          },
          "operator": "Equal",
          "right": {
            "BoolLiteral": true
          }
        }
      },
      "content": [
        {
          "Text": {
            "content": "comparison result equals true\r"
          }
        },
        {
          "Text": {
            "content": "\n"
          }
        }
      ]
    }
  }
]