[
  {
    "List": {
      "span": {
        "start": 0,
        "end": 120
      },
      "open_span": {
        "start": 0,
        "end": 8
      },
      "close_span": {
        "start": 117,
        "end": 120
      },
      "kind": "1",
      "parameters": {
        "1": {
          "span": {
            "start": 8,
            "end": 12
          },
          "key": "1",
          "value": []
        }
      },
      "children": [
        {
          "Item": {
            "span": {
              "start": 12,
              "end": 28
            },
            "open_span": {
              "start": 12,
              "end": 14
            },
            "close_span": {
              "start": 25,
              "end": 27
            },
            "parameters": {},
            "children": [
              {
                "Text": {
                  "span": {
                    "start": 14,
                    "end": 25
                  },
                  "value": "Normal Item"
                }
              }
            ]
          }
        },
        {
          "Conditional": {
            "span": {
              "start": 28,
              "end": 93
            },
            "open_span": {
              "start": 28,
              "end": 34
            },
            "close_span": {
              "start": 89,
              "end": 92
            },
            "condition": {
              "BoolLiteral": {
                "span": {
                  "start": 35,
                  "end": 39
                },
                "value": true
              }
            },
            "items": [
              {
                "span": {
                  "start": 43,
                  "end": 66
                },
                "open_span": {
                  "start": 43,
                  "end": 45
                },
                "close_span": {
                  "start": 63,
                  "end": 65
                },
                "parameters": {},
                "children": [
                  {
                    "Text": {
                      "span": {
                        "start": 45,
                        "end": 63
                      },
                      "value": "Conditional Item 1"
                    }
                  }
                ]
              },
              {
                "span": {
                  "start": 66,
                  "end": 89
                },
                "open_span": {
                  "start": 66,
                  "end": 68
                },
                "close_span": {
                  "start": 86,
                  "end": 88
                },
                "parameters": {},
                "children": [
                  {
                    "Text": {
                      "span": {
                        "start": 68,
                        "end": 86
                      },
                      "value": "Conditional Item 2"
                    }
                  }
                ]
              }
            ]
          }
        },
        {
          "Item": {
            "span": {
              "start": 93,
              "end": 117
            },
            "open_span": {
              "start": 93,
              "end": 95
            },
            "close_span": {
              "start": 114,
              "end": 116
            },
            "parameters": {},
            "children": [
              {
                "Text": {
                  "span": {
                    "start": 95,
                    "end": 114
                  },
                  "value": "Another Normal Item"
                }
              }
            ]
          }
        }
      ]
    }
  }
]