[
  {
    "IfElement": {
      "condition": {
        "And": {
          "operator": {
            "kind": "And"
          },
          "left": {
            "BoolLiteral": {
              "value": true
            }
          },
          "right": {
            "BoolLiteral": {
              "value": true
            }
          }
        }
      },
      "content": [
        {
          "Text": {
            "content": "both true"
          }
        },
        "NewLine"
      ]
    }
  },
  "NewLine",
  "NewLine",
  {
    "IfElement": {
      "condition": {
        "Or": {
          "operator": {
            "kind": "Or"
          },
          "left": {
            "BoolLiteral": {
              "value": true
            }
          },
          "right": {
            "BoolLiteral": {
              "value": false
            }
          }
        }
      },
      "content": [
        {
          "Text": {
            "content": "either true"
          }
        },
        "NewLine"
      ]
    }
  },
  "NewLine",
  "NewLine",
  {
    "IfElement": {
      "condition": {
        "Not": {
          "operator": {
            "kind": "Not"
          },
          "inner": {
            "BoolLiteral": {
              "value": false
            }
          }
        }
      },
      "content": [
        {
          "Text": {
            "content": "not false"
          }
        },
        "NewLine"
      ]
    }
  }
]