[
  {
    "Header": {
      "span": {
        "start": 0,
        "end": 38
      },
      "level": 2,
      "is_folded": false,
      "section_index": 1,
      "children": [
        {
          "Text": {
            "span": {
              "start": 3,
              "end": 37
            },
            "value": "Mathematical Concepts and Formulas"
          }
        }
      ]
    }
  },
  {
    "SoftBreak": {
      "span": {
        "start": 38,
        "end": 39
      }
    }
  },
  {
    "Header": {
      "span": {
        "start": 39,
        "end": 78
      },
      "level": 3,
      "is_folded": false,
      "section_index": 2,
      "children": [
        {
          "Text": {
            "span": {
              "start": 43,
              "end": 77
            },
            "value": "Einstein's Mass-Energy Equivalence"
          }
        }
      ]
    }
  },
  {
    "SoftBreak": {
      "span": {
        "start": 78,
        "end": 79
      }
    }
  },
  {
    "TeX": {
      "span": {
        "start": 79,
        "end": 146
      },
      "open_span": {
        "start": 79,
        "end": 86
      },
      "close_span": {
        "start": 143,
        "end": 146
      },
      "is_block": true,
      "value": "E = mc^2\n"
    }
  },
  {
    "SoftBreak": {
      "span": {
        "start": 146,
        "end": 147
      }
    }
  },
  {
    "SoftBreak": {
      "span": {
        "start": 147,
        "end": 148
      }
    }
  },
  {
    "Text": {
      "span": {
        "start": 148,
        "end": 185
      },
      "value": "This famous equation shows that mass "
    }
  },
  {
    "Italic": {
      "span": {
        "start": 185,
        "end": 190
      },
      "children": [
        {
          "Text": {
            "span": {
              "start": 186,
              "end": 189
            },
            "value": "(m)"
          }
        }
      ]
    }
  },
  {
    "Text": {
      "span": {
        "start": 190,
        "end": 202
      },
      "value": " and energy "
    }
  },
  {
    "Italic": {
      "span": {
        "start": 202,
        "end": 207
      },
      "children": [
        {
          "Text": {
            "span": {
              "start": 203,
              "end": 206
            },
            "value": "(E)"
          }
        }
      ]
    }
  },
  {
    "Text": {
      "span": {
        "start": 207,
        "end": 212
      },
      "value": " are "
    }
  },
  {
    "Bold": {
      "span": {
        "start": 212,
        "end": 231
      },
      "children": [
        {
          "Text": {
            "span": {
              "start": 214,
              "end": 229
            },
            "value": "interchangeable"
          }
        }
      ]
    }
  },
  {
    "Text": {
      "span": {
        "start": 231,
        "end": 232
      },
      "value": ","
    }
  },
  {
    "Text": {
      "span": {
        "start": 232,
        "end": 238
      },
      "value": " with "
    }
  },
  {
    "Italic": {
      "span": {
        "start": 238,
        "end": 241
      },
      "children": [
        {
          "Text": {
            "span": {
              "start": 239,
              "end": 240
            },
            "value": "c"
          }
        }
      ]
    }
  },
  {
    "Text": {
      "span": {
        "start": 241,
        "end": 267
      },
      "value": " being the speed of light."
    }
  },
  {
    "SoftBreak": {
      "span": {
        "start": 267,
        "end": 268
      }
    }
  },
  {
    "SoftBreak": {
      "span": {
        "start": 268,
        "end": 269
      }
    }
  },
  {
    "Fold": {
      "span": {
        "start": 269,
        "end": 674
      },
      "open_span": {
        "start": 269,
        "end": 277
      },
      "close_span": {
        "start": 671,
        "end": 674
      },
      "parameters": {
        "bgcolor": {
          "span": {
            "start": 278,
            "end": 300
          },
          "key": "bgcolor",
          "value": [
            {
              "Text": {
                "span": {
                  "start": 288,
                  "end": 299
                },
                "value": "lightyellow"
              }
            }
          ]
        }
      },
      "summary": {
        "span": {
          "start": 301,
          "end": 331
        },
        "open_span": {
          "start": 301,
          "end": 303
        },
        "close_span": {
          "start": 328,
          "end": 330
        },
        "parameters": {},
        "children": [
          {
            "Bold": {
              "span": {
                "start": 303,
                "end": 323
              },
              "children": [
                {
                  "Text": {
                    "span": {
                      "start": 305,
                      "end": 321
                    },
                    "value": "Derivation Steps"
                  }
                }
              ]
            }
          },
          {
            "Text": {
              "span": {
                "start": 323,
                "end": 328
              },
              "value": " 📚"
            }
          }
        ]
      },
      "details": {
        "span": {
          "start": 331,
          "end": 671
        },
        "open_span": {
          "start": 331,
          "end": 333
        },
        "close_span": {
          "start": 668,
          "end": 670
        },
        "parameters": {},
        "children": [
          {
            "List": {
              "span": {
                "start": 334,
                "end": 506
              },
              "open_span": {
                "start": 334,
                "end": 342
              },
              "close_span": {
                "start": 503,
                "end": 506
              },
              "kind": "1",
              "parameters": {
                "1": {
                  "span": {
                    "start": 343,
                    "end": 345
                  },
                  "key": "1",
                  "value": []
                }
              },
              "children": [
                {
                  "Item": {
                    "span": {
                      "start": 346,
                      "end": 411
                    },
                    "open_span": {
                      "start": 346,
                      "end": 348
                    },
                    "close_span": {
                      "start": 408,
                      "end": 410
                    },
                    "parameters": {},
                    "children": [
                      {
                        "Text": {
                          "span": {
                            "start": 348,
                            "end": 382
                          },
                          "value": "Start with relativistic momentum: "
                        }
                      },
                      {
                        "TeX": {
                          "span": {
                            "start": 382,
                            "end": 407
                          },
                          "open_span": {
                            "start": 382,
                            "end": 389
                          },
                          "close_span": {
                            "start": 404,
                            "end": 407
                          },
                          "is_block": false,
                          "value": "p = \\gamma mv\n"
                        }
                      }
                    ]
                  }
                },
                {
                  "Item": {
                    "span": {
                      "start": 411,
                      "end": 446
                    },
                    "open_span": {
                      "start": 411,
                      "end": 413
                    },
                    "close_span": {
                      "start": 443,
                      "end": 445
                    },
                    "parameters": {},
                    "children": [
                      {
                        "Text": {
                          "span": {
                            "start": 413,
                            "end": 443
                          },
                          "value": "Apply energy-momentum relation"
                        }
                      }
                    ]
                  }
                },
                {
                  "Item": {
                    "span": {
                      "start": 446,
                      "end": 478
                    },
                    "open_span": {
                      "start": 446,
                      "end": 448
                    },
                    "close_span": {
                      "start": 475,
                      "end": 477
                    },
                    "parameters": {},
                    "children": [
                      {
                        "Text": {
                          "span": {
                            "start": 448,
                            "end": 475
                          },
                          "value": "Simplify for rest mass case"
                        }
                      }
                    ]
                  }
                },
                {
                  "Item": {
                    "span": {
                      "start": 478,
                      "end": 503
                    },
                    "open_span": {
                      "start": 478,
                      "end": 480
                    },
                    "close_span": {
                      "start": 500,
                      "end": 502
                    },
                    "parameters": {},
                    "children": [
                      {
                        "Text": {
                          "span": {
                            "start": 480,
                            "end": 488
                          },
                          "value": "Result: "
                        }
                      },
                      {
                        "Bold": {
                          "span": {
                            "start": 488,
                            "end": 500
                          },
                          "children": [
                            {
                              "Text": {
                                "span": {
                                  "start": 490,
                                  "end": 498
                                },
                                "value": "E = mc²"
                              }
                            }
                          ]
                        }
                      }
                    ]
                  }
                }
              ]
            }
          },
          {
            "SoftBreak": {
              "span": {
                "start": 506,
                "end": 507
              }
            }
          },
          {
            "SoftBreak": {
              "span": {
                "start": 507,
                "end": 508
              }
            }
          },
          {
            "BlockQuote": {
              "span": {
                "start": 508,
                "end": 666
              },
              "open_span": {
                "start": 508,
                "end": 517
              },
              "close_span": {
                "start": 663,
                "end": 666
              },
              "parameters": {
                "style": {
                  "span": {
                    "start": 518,
                    "end": 575
                  },
                  "key": "style",
                  "value": [
                    {
                      "Text": {
                        "span": {
                          "start": 526,
                          "end": 574
                        },
                        "value": "border-left:3px solid #007acc; padding-left:15px"
                      }
                    }
                  ]
                }
              },
              "children": [
                {
                  "Text": {
                    "span": {
                      "start": 576,
                      "end": 640
                    },
                    "value": "\"The most beautiful thing we can experience is the mysterious.\" "
                  }
                },
                {
                  "SoftBreak": {
                    "span": {
                      "start": 640,
                      "end": 641
                    }
                  }
                },
                {
                  "Text": {
                    "span": {
                      "start": 641,
                      "end": 645
                    },
                    "value": "— "
                  }
                },
                {
                  "Italic": {
                    "span": {
                      "start": 645,
                      "end": 662
                    },
                    "children": [
                      {
                        "Text": {
                          "span": {
                            "start": 646,
                            "end": 661
                          },
                          "value": "Albert Einstein"
                        }
                      }
                    ]
                  }
                },
                {
                  "SoftBreak": {
                    "span": {
                      "start": 662,
                      "end": 663
                    }
                  }
                }
              ]
            }
          },
          {
            "Text": {
              "span": {
                "start": 666,
                "end": 667
              },
              "value": "w"
            }
          }
        ]
      }
    }
  },
  {
    "SoftBreak": {
      "span": {
        "start": 674,
        "end": 675
      }
    }
  },
  {
    "SoftBreak": {
      "span": {
        "start": 675,
        "end": 676
      }
    }
  },
  {
    "Header": {
      "span": {
        "start": 676,
        "end": 711
      },
      "level": 3,
      "is_folded": false,
      "section_index": 3,
      "children": [
        {
          "Text": {
            "span": {
              "start": 680,
              "end": 710
            },
            "value": "Applications in Modern Physics"
          }
        }
      ]
    }
  },
  {
    "SoftBreak": {
      "span": {
        "start": 711,
        "end": 712
      }
    }
  },
  {
    "Table": {
      "span": {
        "start": 712,
        "end": 1105
      },
      "open_span": {
        "start": 712,
        "end": 721
      },
      "close_span": {
        "start": 1102,
        "end": 1105
      },
      "parameters": {
        "style": {
          "span": {
            "start": 722,
            "end": 765
          },
          "key": "style",
          "value": [
            {
              "Text": {
                "span": {
                  "start": 730,
                  "end": 764
                },
                "value": "margin:10px; border:1px solid #ccc"
              }
            }
          ]
        }
      },
      "children": [
        {
          "Row": {
            "span": {
              "start": 766,
              "end": 820
            },
            "open_span": {
              "start": 766,
              "end": 768
            },
            "close_span": {
              "start": 817,
              "end": 819
            },
            "parameters": {},
            "children": [
              {
                "Cell": {
                  "span": {
                    "start": 768,
                    "end": 782
                  },
                  "open_span": {
                    "start": 768,
                    "end": 770
                  },
                  "close_span": {
                    "start": 779,
                    "end": 781
                  },
                  "parameters": {},
                  "children": [
                    {
                      "Bold": {
                        "span": {
                          "start": 770,
                          "end": 779
                        },
                        "children": [
                          {
                            "Text": {
                              "span": {
                                "start": 772,
                                "end": 777
                              },
                              "value": "Field"
                            }
                          }
                        ]
                      }
                    }
                  ]
                }
              },
              {
                "Cell": {
                  "span": {
                    "start": 782,
                    "end": 802
                  },
                  "open_span": {
                    "start": 782,
                    "end": 784
                  },
                  "close_span": {
                    "start": 799,
                    "end": 801
                  },
                  "parameters": {},
                  "children": [
                    {
                      "Bold": {
                        "span": {
                          "start": 784,
                          "end": 799
                        },
                        "children": [
                          {
                            "Text": {
                              "span": {
                                "start": 786,
                                "end": 797
                              },
                              "value": "Application"
                            }
                          }
                        ]
                      }
                    }
                  ]
                }
              },
              {
                "Cell": {
                  "span": {
                    "start": 802,
                    "end": 817
                  },
                  "open_span": {
                    "start": 802,
                    "end": 804
                  },
                  "close_span": {
                    "start": 815,
                    "end": 817
                  },
                  "parameters": {},
                  "children": [
                    {
                      "Bold": {
                        "span": {
                          "start": 804,
                          "end": 815
                        },
                        "children": [
                          {
                            "Text": {
                              "span": {
                                "start": 806,
                                "end": 813
                              },
                              "value": "Formula"
                            }
                          }
                        ]
                      }
                    }
                  ]
                }
              }
            ]
          }
        },
        {
          "Row": {
            "span": {
              "start": 820,
              "end": 917
            },
            "open_span": {
              "start": 820,
              "end": 822
            },
            "close_span": {
              "start": 914,
              "end": 916
            },
            "parameters": {},
            "children": [
              {
                "Cell": {
                  "span": {
                    "start": 822,
                    "end": 842
                  },
                  "open_span": {
                    "start": 822,
                    "end": 824
                  },
                  "close_span": {
                    "start": 839,
                    "end": 841
                  },
                  "parameters": {},
                  "children": [
                    {
                      "Text": {
                        "span": {
                          "start": 824,
                          "end": 839
                        },
                        "value": "Nuclear Physics"
                      }
                    }
                  ]
                }
              },
              {
                "Cell": {
                  "span": {
                    "start": 842,
                    "end": 874
                  },
                  "open_span": {
                    "start": 842,
                    "end": 844
                  },
                  "close_span": {
                    "start": 871,
                    "end": 873
                  },
                  "parameters": {},
                  "children": [
                    {
                      "Text": {
                        "span": {
                          "start": 844,
                          "end": 871
                        },
                        "value": "Binding energy calculations"
                      }
                    }
                  ]
                }
              },
              {
                "Cell": {
                  "span": {
                    "start": 874,
                    "end": 914
                  },
                  "open_span": {
                    "start": 874,
                    "end": 876
                  },
                  "close_span": {
                    "start": 912,
                    "end": 914
                  },
                  "parameters": {},
                  "children": [
                    {
                      "TeX": {
                        "span": {
                          "start": 876,
                          "end": 911
                        },
                        "open_span": {
                          "start": 876,
                          "end": 883
                        },
                        "close_span": {
                          "start": 908,
                          "end": 911
                        },
                        "is_block": false,
                        "value": "\\Delta E = \\Delta m c^2\n"
                      }
                    }
                  ]
                }
              }
            ]
          }
        },
        {
          "Row": {
            "span": {
              "start": 917,
              "end": 1016
            },
            "open_span": {
              "start": 917,
              "end": 919
            },
            "close_span": {
              "start": 1013,
              "end": 1015
            },
            "parameters": {},
            "children": [
              {
                "Cell": {
                  "span": {
                    "start": 919,
                    "end": 940
                  },
                  "open_span": {
                    "start": 919,
                    "end": 921
                  },
                  "close_span": {
                    "start": 937,
                    "end": 939
                  },
                  "parameters": {},
                  "children": [
                    {
                      "Text": {
                        "span": {
                          "start": 921,
                          "end": 937
                        },
                        "value": "Particle Physics"
                      }
                    }
                  ]
                }
              },
              {
                "Cell": {
                  "span": {
                    "start": 940,
                    "end": 979
                  },
                  "open_span": {
                    "start": 940,
                    "end": 942
                  },
                  "close_span": {
                    "start": 976,
                    "end": 978
                  },
                  "parameters": {},
                  "children": [
                    {
                      "Text": {
                        "span": {
                          "start": 942,
                          "end": 976
                        },
                        "value": "Particle-antiparticle annihilation"
                      }
                    }
                  ]
                }
              },
              {
                "Cell": {
                  "span": {
                    "start": 979,
                    "end": 1013
                  },
                  "open_span": {
                    "start": 979,
                    "end": 981
                  },
                  "close_span": {
                    "start": 1011,
                    "end": 1013
                  },
                  "parameters": {},
                  "children": [
                    {
                      "TeX": {
                        "span": {
                          "start": 981,
                          "end": 1010
                        },
                        "open_span": {
                          "start": 981,
                          "end": 988
                        },
                        "close_span": {
                          "start": 1007,
                          "end": 1010
                        },
                        "is_block": false,
                        "value": "E_{total} = 2mc^2\n"
                      }
                    }
                  ]
                }
              }
            ]
          }
        },
        {
          "Row": {
            "span": {
              "start": 1016,
              "end": 1102
            },
            "open_span": {
              "start": 1016,
              "end": 1018
            },
            "close_span": {
              "start": 1099,
              "end": 1101
            },
            "parameters": {},
            "children": [
              {
                "Cell": {
                  "span": {
                    "start": 1018,
                    "end": 1032
                  },
                  "open_span": {
                    "start": 1018,
                    "end": 1020
                  },
                  "close_span": {
                    "start": 1029,
                    "end": 1031
                  },
                  "parameters": {},
                  "children": [
                    {
                      "Text": {
                        "span": {
                          "start": 1020,
                          "end": 1029
                        },
                        "value": "Cosmology"
                      }
                    }
                  ]
                }
              },
              {
                "Cell": {
                  "span": {
                    "start": 1032,
                    "end": 1062
                  },
                  "open_span": {
                    "start": 1032,
                    "end": 1034
                  },
                  "close_span": {
                    "start": 1059,
                    "end": 1061
                  },
                  "parameters": {},
                  "children": [
                    {
                      "Text": {
                        "span": {
                          "start": 1034,
                          "end": 1059
                        },
                        "value": "Stellar energy production"
                      }
                    }
                  ]
                }
              },
              {
                "Cell": {
                  "span": {
                    "start": 1062,
                    "end": 1099
                  },
                  "open_span": {
                    "start": 1062,
                    "end": 1064
                  },
                  "close_span": {
                    "start": 1097,
                    "end": 1099
                  },
                  "parameters": {},
                  "children": [
                    {
                      "TeX": {
                        "span": {
                          "start": 1064,
                          "end": 1096
                        },
                        "open_span": {
                          "start": 1064,
                          "end": 1071
                        },
                        "close_span": {
                          "start": 1093,
                          "end": 1096
                        },
                        "is_block": false,
                        "value": "L = \\frac{dm}{dt}c^2\n"
                      }
                    }
                  ]
                }
              }
            ]
          }
        }
      ]
    }
  },
  {
    "SoftBreak": {
      "span": {
        "start": 1105,
        "end": 1106
      }
    }
  },
  {
    "SoftBreak": {
      "span": {
        "start": 1106,
        "end": 1107
      }
    }
  },
  {
    "Header": {
      "span": {
        "start": 1107,
        "end": 1129
      },
      "level": 3,
      "is_folded": false,
      "section_index": 4,
      "children": [
        {
          "Text": {
            "span": {
              "start": 1111,
              "end": 1128
            },
            "value": "Related Constants"
          }
        }
      ]
    }
  },
  {
    "SoftBreak": {
      "span": {
        "start": 1129,
        "end": 1130
      }
    }
  },
  {
    "Text": {
      "span": {
        "start": 1130,
        "end": 1159
      },
      "value": "Important physical constants "
    }
  },
  {
    "Italic": {
      "span": {
        "start": 1159,
        "end": 1183
      },
      "children": [
        {
          "Text": {
            "span": {
              "start": 1160,
              "end": 1176
            },
            "value": "(measured as of "
          }
        },
        {
          "TimeNow": {
            "span": {
              "start": 1176,
              "end": 1181
            }
          }
        },
        {
          "Text": {
            "span": {
              "start": 1181,
              "end": 1182
            },
            "value": ")"
          }
        }
      ]
    }
  },
  {
    "Text": {
      "span": {
        "start": 1183,
        "end": 1184
      },
      "value": ":"
    }
  },
  {
    "SoftBreak": {
      "span": {
        "start": 1184,
        "end": 1185
      }
    }
  },
  {
    "SoftBreak": {
      "span": {
        "start": 1185,
        "end": 1186
      }
    }
  },
  {
    "List": {
      "span": {
        "start": 1186,
        "end": 1381
      },
      "open_span": {
        "start": 1186,
        "end": 1194
      },
      "close_span": {
        "start": 1378,
        "end": 1381
      },
      "kind": "i",
      "parameters": {
        "i": {
          "span": {
            "start": 1195,
            "end": 1197
          },
          "key": "i",
          "value": []
        },
        "style": {
          "span": {
            "start": 1198,
            "end": 1228
          },
          "key": "style",
          "value": [
            {
              "Text": {
                "span": {
                  "start": 1206,
                  "end": 1227
                },
                "value": "font-family:monospace"
              }
            }
          ]
        }
      },
      "children": [
        {
          "Item": {
            "span": {
              "start": 1229,
              "end": 1271
            },
            "open_span": {
              "start": 1229,
              "end": 1231
            },
            "close_span": {
              "start": 1268,
              "end": 1270
            },
            "parameters": {},
            "children": [
              {
                "Text": {
                  "span": {
                    "start": 1231,
                    "end": 1255
                  },
                  "value": "Speed of light: `c = 299"
                }
              },
              {
                "Text": {
                  "span": {
                    "start": 1255,
                    "end": 1256
                  },
                  "value": ","
                }
              },
              {
                "Text": {
                  "span": {
                    "start": 1256,
                    "end": 1259
                  },
                  "value": "792"
                }
              },
              {
                "Text": {
                  "span": {
                    "start": 1259,
                    "end": 1260
                  },
                  "value": ","
                }
              },
              {
                "Text": {
                  "span": {
                    "start": 1260,
                    "end": 1265
                  },
                  "value": "458 m"
                }
              },
              {
                "Text": {
                  "span": {
                    "start": 1265,
                    "end": 1266
                  },
                  "value": "/"
                }
              },
              {
                "Text": {
                  "span": {
                    "start": 1266,
                    "end": 1268
                  },
                  "value": "s`"
                }
              }
            ]
          }
        },
        {
          "Item": {
            "span": {
              "start": 1271,
              "end": 1324
            },
            "open_span": {
              "start": 1271,
              "end": 1273
            },
            "close_span": {
              "start": 1321,
              "end": 1323
            },
            "parameters": {},
            "children": [
              {
                "Text": {
                  "span": {
                    "start": 1273,
                    "end": 1321
                  },
                  "value": "Planck constant: `h = 6.626 × 10⁻³⁴ J⋅s`"
                }
              }
            ]
          }
        },
        {
          "Item": {
            "span": {
              "start": 1324,
              "end": 1378
            },
            "open_span": {
              "start": 1324,
              "end": 1326
            },
            "close_span": {
              "start": 1375,
              "end": 1377
            },
            "parameters": {},
            "children": [
              {
                "Text": {
                  "span": {
                    "start": 1326,
                    "end": 1345
                  },
                  "value": "Avogadro number: `N"
                }
              },
              {
                "Text": {
                  "span": {
                    "start": 1345,
                    "end": 1346
                  },
                  "value": "_"
                }
              },
              {
                "Text": {
                  "span": {
                    "start": 1346,
                    "end": 1375
                  },
                  "value": "A = 6.022 × 10²³ mol⁻¹`"
                }
              }
            ]
          }
        }
      ]
    }
  },
  {
    "SoftBreak": {
      "span": {
        "start": 1381,
        "end": 1382
      }
    }
  },
  {
    "SoftBreak": {
      "span": {
        "start": 1382,
        "end": 1383
      }
    }
  },
  {
    "Header": {
      "span": {
        "start": 1383,
        "end": 1413
      },
      "level": 3,
      "is_folded": false,
      "section_index": 5,
      "children": [
        {
          "Text": {
            "span": {
              "start": 1387,
              "end": 1412
            },
            "value": "Experimental Verification"
          }
        }
      ]
    }
  },
  {
    "SoftBreak": {
      "span": {
        "start": 1413,
        "end": 1414
      }
    }
  },
  {
    "Code": {
      "span": {
        "start": 1414,
        "end": 1757
      },
      "open_span": {
        "start": 1414,
        "end": 1422
      },
      "close_span": {
        "start": 1754,
        "end": 1757
      },
      "parameters": {
        "lang": {
          "span": {
            "start": 1423,
            "end": 1437
          },
          "key": "lang",
          "value": [
            {
              "Text": {
                "span": {
                  "start": 1430,
                  "end": 1436
                },
                "value": "python"
              }
            }
          ]
        },
        "style": {
          "span": {
            "start": 1438,
            "end": 1465
          },
          "key": "style",
          "value": [
            {
              "Text": {
                "span": {
                  "start": 1446,
                  "end": 1464
                },
                "value": "background:#f5f5f5"
              }
            }
          ]
        }
      },
      "value": "# Simple energy calculation\ndef mass_energy_equiv(mass_kg):\n    \"\"\"Calculate energy from mass using E=mc²\"\"\"\n    c = 299792458  # m/s\n    energy_joules = mass_kg * c**2\n    return energy_joules\n\n# Example: 1 gram of matter\nprint(f\"Energy from 1g: {mass_energy_equiv(0.001):.2e} Joules\")\n"
    }
  },
  {
    "SoftBreak": {
      "span": {
        "start": 1757,
        "end": 1758
      }
    }
  },
  {
    "SoftBreak": {
      "span": {
        "start": 1758,
        "end": 1759
      }
    }
  },
  {
    "Fold": {
      "span": {
        "start": 1759,
        "end": 2214
      },
      "open_span": {
        "start": 1759,
        "end": 1767
      },
      "close_span": {
        "start": 2211,
        "end": 2214
      },
      "parameters": {},
      "summary": {
        "span": {
          "start": 1767,
          "end": 1800
        },
        "open_span": {
          "start": 1768,
          "end": 1770
        },
        "close_span": {
          "start": 1797,
          "end": 1799
        },
        "parameters": {},
        "children": [
          {
            "Bold": {
              "span": {
                "start": 1770,
                "end": 1789
              },
              "children": [
                {
                  "Text": {
                    "span": {
                      "start": 1772,
                      "end": 1787
                    },
                    "value": "Historical Note"
                  }
                }
              ]
            }
          },
          {
            "Text": {
              "span": {
                "start": 1789,
                "end": 1797
              },
              "value": " 🏛️"
            }
          }
        ]
      },
      "details": {
        "span": {
          "start": 1800,
          "end": 2211
        },
        "open_span": {
          "start": 1800,
          "end": 1802
        },
        "close_span": {
          "start": 2208,
          "end": 2210
        },
        "parameters": {},
        "children": [
          {
            "Text": {
              "span": {
                "start": 1803,
                "end": 1834
              },
              "value": "This equation was published in "
            }
          },
          {
            "Bold": {
              "span": {
                "start": 1834,
                "end": 1842
              },
              "children": [
                {
                  "Text": {
                    "span": {
                      "start": 1836,
                      "end": 1840
                    },
                    "value": "1905"
                  }
                }
              ]
            }
          },
          {
            "Text": {
              "span": {
                "start": 1842,
                "end": 1865
              },
              "value": " as part of Einstein's "
            }
          },
          {
            "Italic": {
              "span": {
                "start": 1865,
                "end": 1885
              },
              "children": [
                {
                  "Text": {
                    "span": {
                      "start": 1866,
                      "end": 1884
                    },
                    "value": "special relativity"
                  }
                }
              ]
            }
          },
          {
            "Text": {
              "span": {
                "start": 1885,
                "end": 1892
              },
              "value": " paper."
            }
          },
          {
            "SoftBreak": {
              "span": {
                "start": 1892,
                "end": 1893
              }
            }
          },
          {
            "Text": {
              "span": {
                "start": 1893,
                "end": 1915
              },
              "value": "The paper was titled \""
            }
          },
          {
            "Underline": {
              "span": {
                "start": 1915,
                "end": 1987
              },
              "children": [
                {
                  "Text": {
                    "span": {
                      "start": 1917,
                      "end": 1985
                    },
                    "value": "Ist die Trägheit eines Körpers von seinem Energieinhalt abhängig?"
                  }
                }
              ]
            }
          },
          {
            "Text": {
              "span": {
                "start": 1987,
                "end": 1988
              },
              "value": "\""
            }
          },
          {
            "SoftBreak": {
              "span": {
                "start": 1988,
                "end": 1989
              }
            }
          },
          {
            "SoftBreak": {
              "span": {
                "start": 1989,
                "end": 1990
              }
            }
          },
          {
            "Text": {
              "span": {
                "start": 1990,
                "end": 2009
              },
              "value": "Fun fact: Einstein "
            }
          },
          {
            "Strikethrough": {
              "span": {
                "start": 2009,
                "end": 2022
              },
              "children": [
                {
                  "Text": {
                    "span": {
                      "start": 2011,
                      "end": 2020
                    },
                    "value": "initially"
                  }
                }
              ]
            }
          },
          {
            "Text": {
              "span": {
                "start": 2022,
                "end": 2068
              },
              "value": " didn't receive the Nobel Prize for relativity"
            }
          },
          {
            "Text": {
              "span": {
                "start": 2068,
                "end": 2069
              },
              "value": ","
            }
          },
          {
            "Text": {
              "span": {
                "start": 2069,
                "end": 2070
              },
              "value": " "
            }
          },
          {
            "SoftBreak": {
              "span": {
                "start": 2070,
                "end": 2071
              }
            }
          },
          {
            "Text": {
              "span": {
                "start": 2071,
                "end": 2095
              },
              "value": "but for his work on the "
            }
          },
          {
            "Superscript": {
              "span": {
                "start": 2095,
                "end": 2112
              },
              "children": [
                {
                  "Text": {
                    "span": {
                      "start": 2097,
                      "end": 2110
                    },
                    "value": "photoelectric"
                  }
                }
              ]
            }
          },
          {
            "Text": {
              "span": {
                "start": 2112,
                "end": 2120
              },
              "value": " effect!"
            }
          },
          {
            "SoftBreak": {
              "span": {
                "start": 2120,
                "end": 2121
              }
            }
          },
          {
            "SoftBreak": {
              "span": {
                "start": 2121,
                "end": 2122
              }
            }
          },
          {
            "Comment": {
              "span": {
                "start": 2122,
                "end": 2207
              },
              "value": " Einstein's original paper can be found in \n   Annalen der Physik, vol. 18, 1905 "
            }
          }
        ]
      }
    }
  },
  {
    "SoftBreak": {
      "span": {
        "start": 2214,
        "end": 2215
      }
    }
  },
  {
    "SoftBreak": {
      "span": {
        "start": 2215,
        "end": 2216
      }
    }
  },
  {
    "HLine": {
      "span": {
        "start": 2216,
        "end": 2220
      }
    }
  },
  {
    "SoftBreak": {
      "span": {
        "start": 2220,
        "end": 2221
      }
    }
  },
  {
    "Italic": {
      "span": {
        "start": 2221,
        "end": 2276
      },
      "children": [
        {
          "Text": {
            "span": {
              "start": 2222,
              "end": 2275
            },
            "value": "Mathematical notation powered by SevenMark TeX engine"
          }
        }
      ]
    }
  },
  {
    "Text": {
      "span": {
        "start": 2276,
        "end": 2278
      },
      "value": "  "
    }
  },
  {
    "SoftBreak": {
      "span": {
        "start": 2278,
        "end": 2279
      }
    }
  },
  {
    "Italic": {
      "span": {
        "start": 2279,
        "end": 2308
      },
      "children": [
        {
          "Text": {
            "span": {
              "start": 2280,
              "end": 2302
            },
            "value": "Document generated on "
          }
        },
        {
          "TimeNow": {
            "span": {
              "start": 2302,
              "end": 2307
            }
          }
        }
      ]
    }
  },
  {
    "SoftBreak": {
      "span": {
        "start": 2308,
        "end": 2309
      }
    }
  }
]